autoboost/__init__.py
autoboost/const.py
autoboost/optimizer.py
autoboost-20.8.15.dist-info/LICENCE
autoboost-20.8.15.dist-info/METADATA
autoboost-20.8.15.dist-info/WHEEL
autoboost-20.8.15.dist-info/top_level.txt
autoboost-20.8.15.dist-info/RECORD
