Metadata-Version: 2.1
Name: autoboost
Version: 20.8.15
Summary: A thin wrapper for step-wise parameter optimization of boosting algorithms.
Author: Sven H. Giese
Author-email: sven.giese88@gmail.com
Project-URL: Bug Tracker, https://github.com/gieses/autoboost/issues
Project-URL: Source Code, https://github.com/gieses/autoboost
Keywords: xgboost,lightgbm,sklearn,optimization
Classifier: Programming Language :: Python
Classifier: Programming Language :: Python :: 3.9
Classifier: Programming Language :: Python :: 3.10
Classifier: Programming Language :: Python :: Implementation :: PyPy
Requires-Python: >=3.9
License-File: LICENCE
Requires-Dist: xgboost
Requires-Dist: lightgbm
Requires-Dist: scikit-learn
Requires-Dist: seaborn
Requires-Dist: matplotlib
Requires-Dist: numpy
Requires-Dist: tqdm
